{
  "tasks": [
    {
      "title": "lajdflk",
      "created_at": "16:20 12/10/2020",
      "completed": true,
      "id": 1
    },
    {
      "title": "kdjflkasdjf",
      "created_at": "16:20 12/10/2020",
      "completed": true,
      "id": 2
    },
    {
      "title": "jaslkdfjasdl",
      "created_at": "16:20 12/10/2020",
      "completed": true,
      "id": 3
    },
    {
      "title": "jflkasjd",
      "created_at": "16:20 12/10/2020",
      "completed": false,
      "id": 4
    },
    {
      "title": "dlkajflksdj",
      "created_at": "16:20 12/10/2020",
      "completed": false,
      "id": 5
    },
    {
      "title": "kajfkljads",
      "created_at": "16:20 12/10/2020",
      "completed": false,
      "id": 6
    },
    {
      "title": "lkjasdlkfjs",
      "created_at": "16:20 12/10/2020",
      "completed": false,
      "id": 7
    }
  ]
}